prot2token/__init__.py
prot2token/models.py
prot2token/utils.py
prot2token-0.3.0.dist-info/licenses/LICENSE
prot2token-0.3.0.dist-info/METADATA
prot2token-0.3.0.dist-info/WHEEL
prot2token-0.3.0.dist-info/top_level.txt
prot2token-0.3.0.dist-info/RECORD
