Metadata-Version: 2.4
Name: prot2token
Version: 0.3.0
Summary: A simple machine learning package using scikit-learn
Author-email: Mahdi <mahdipoormirzaie@gmail.com>
License: AGPL-3.0
Project-URL: Homepage, https://github.com/mahdip72/prot2token/prot2token
Requires-Python: >=3.6
License-File: LICENSE
Requires-Dist: torch>=2.0.0
Requires-Dist: transformers>=4.0.0
Requires-Dist: peft
Requires-Dist: timm
Requires-Dist: python-box
Requires-Dist: pandas
Dynamic: license-file
